cipcore/__init__.py
cipcore/access_token_client.py
cipcore/delivery_ef.py
cipcore/file_copy.py
cipcore/ftp_service.py
cipcore/mailer.py
cipcore/redis_checker.py
cipcore/requester.py
cipcore/retrying.py
cipcore/V2/__init__.py
cipcore/V2/mailer.py
cipcore/core/__init__.py
cipcore/core/decorator.py
cipcore/core/helpers.py
tests/__init__.py
tests/test_delivery_ef_publish_request.py
tests/test_email.py
tests/test_file_copy.py
tests/test_ftp_service.py
tests/test_http_service.py
tests/test_redis_checker.py
tests/test_token_api.py
tests/test_v2_email.py
cipcore-1.0.22.dist-info/METADATA
cipcore-1.0.22.dist-info/WHEEL
cipcore-1.0.22.dist-info/top_level.txt
cipcore-1.0.22.dist-info/RECORD
